ms_utils/__init__.py
ms_utils/abort.py
ms_utils/abstract_model.py
ms_utils/authentication.py
ms_utils/binary_uuid.py
ms_utils/deploy.py
ms_utils/func_date.py
ms_utils/function_utils.py
ms_utils/generic_crud_class.py
ms_utils/generic_pagination.py
ms_utils/logger.py
ms_utils/model_utils.py
ms_utils/prepare_json_response.py
ms_utils/requests_utils.py
ms_utils/schema_utils.py
ms_utils/validation_utils.py
ms_utils/view_utils.py
ms_utils/devops/Dockerfile
ms_utils/devops/Jenkinsfile
ms_utils/devops/docker-compose.yml
ms_utils/devops/deploy/script.sh
ms_utils/looker_studio/__init__.py
ms_utils/looker_studio/looker_studio.py
ms_utils/utils/__init__.py
ms_utils/utils/utils.py
ms_utils/utils/looker_studio/__init__.py
ms_utils/utils/looker_studio/methods.py
ms_utils/utils/webdriver/__init__.py
ms_utils/utils/webdriver/configurations.py
ms_utils/utils/webdriver/methods.py
ms_general_utils-2.2.0.dist-info/LICENSE.txt
ms_general_utils-2.2.0.dist-info/METADATA
ms_general_utils-2.2.0.dist-info/WHEEL
ms_general_utils-2.2.0.dist-info/entry_points.txt
ms_general_utils-2.2.0.dist-info/top_level.txt
ms_general_utils-2.2.0.dist-info/RECORD
