Metadata-Version: 2.1
Name: ms_general_utils
Version: 2.2.0
Summary: General functions for the implementation of microservices.
Home-page: https://github.com/rgramos/ms-utils.git
License: GPLv3
Classifier: Programming Language :: Python :: 3
Classifier: License :: OSI Approved :: GNU General Public License v3 (GPLv3)
License-File: LICENSE.txt
